devind_yearfrac/__init__.py
devind_yearfrac/act_afb.py
devind_yearfrac/act_isda.py
devind_yearfrac/d30360e.py
devind_yearfrac/d30365.py
devind_yearfrac/isaleapyear.py
devind_yearfrac/julianday.py
devind_yearfrac/method_factory.py
devind_yearfrac/yearfrac.py
devind_yearfrac-1.0.0.dist-info/METADATA
devind_yearfrac-1.0.0.dist-info/WHEEL
devind_yearfrac-1.0.0.dist-info/LICENSE
devind_yearfrac-1.0.0.dist-info/RECORD
