Metadata-Version: 2.1
Name: devind-yearfrac
Version: 1.0.0
Summary: Daycount methods to compute date differences in year units
Home-page: https://github.com/devind-team/devind_yearfrac
License: MIT
Author: Ulf Hamster
Author-email: 554c46@gmail.com
Requires-Python: >=3.9
Classifier: License :: OSI Approved :: MIT License
Classifier: Programming Language :: Python :: 3
Classifier: Programming Language :: Python :: 3.9
Classifier: Programming Language :: Python :: 3.10
Classifier: Programming Language :: Python :: 3.11
Requires-Dist: numpy (>=1.24.1,<2.0.0)
Project-URL: Repository, https://github.com/devind-team/devind_yearfrac
